{
"站名":"fff996",
"主页url":"https://aea998.com",
"直接播放":"1",
//"数组":"<li class=\"content-item\">&&<li>",
"图片":"lazy\" data-original=\"&&\"",
"标题":"title=\"&&\"",
"链接":"href=\"/vodhtml/&&\"",
"链接前缀":"https://aea998.com/vodplayhtml/",
"链接后缀":"index_1_1.html",
//"副标题":"<span color=\"metadata-view\">&&</span>",
"简介":"<p>&&</p>",
"免嗅":"0",
"嗅探词":".m3u8#.mp4#.flv#.m4a#.avi#.mkv#.mov#.3gp#.asf#.rm#.rmvb#.wmv#.mpg#.mpeg#.mpe#.ts#.vob#.mp3#.wma",
"分类":"国产$21#日本$20#swag$22#原创$31#欧美$33#传媒$24#cosplay$29",
"分类url":"https://aea998.com/vodtypehtml/{cateId}/index_{catePg}.html[https://aea998.com/vodtypehtml/{cateId}]"
}