{
"站名":"久久乐",
"主页url":"https://www.jiujiule6.xyz",
//发布 https://www.jjll01.xyz/
"直接播放":"1",
"图片":"src=\"&&\"",
"标题":"title=\"&&\"",
"链接":"href=\"&&\"",
"简介":"<p>&&</p>",
"搜索模式":"1",
"搜索url":"/search/{wd}/{pg}",
"搜索图片":"src=\"&&\"",
"搜索标题":"title=\"&&\"",
"搜索链接":"href=\"&&\"",
"免嗅":"0",
"分类":"国产$daluhuaren#中字$zimuzhongwen#主播$wanghongshipin#人妻$linjiarenqi#丝袜$siwameitui#推荐$quanwangtuijian#欧美$oumeipian#无码$wumashipin#制服$zhifuyouhuo#乱伦$qiangbao#日韩$rihanav#HEYZO$heyzo#DMM$dmm#HEY$hey#",
"分类url":"https://www.jiujiule6.xyz/categories/{cateId}/{catePg}[https://www.jiujiule6.xyz/categories/{cateId}/]"
}